sparc/__init__.py
sparc/api.py
sparc/calculator.py
sparc/cli.py
sparc/client.py
sparc/common.py
sparc/docparser.py
sparc/download_data.py
sparc/io.py
sparc/quicktest.py
sparc/socketio.py
sparc/utils.py
sparc/psp/01_H_1_1.0_1.0_pbe_v1.0.psp8
sparc/psp/02_He_2_1.1_1.2_pbe_v1.0.psp8
sparc/psp/03_Li_3_1.6_1.6_pbe_v1.0.psp8
sparc/psp/04_Be_4_1.8_1.9_pbe_v1.0.psp8
sparc/psp/05_B_3_1.5_1.7_pbe_n_v1.0.psp8
sparc/psp/06_C_4_1.2_1.2_pbe_n_v1.0.psp8
sparc/psp/07_N_5_1.2_1.4_pbe_n_v1.0.psp8
sparc/psp/08_O_6_1.2_1.4_pbe_n_v1.0.psp8
sparc/psp/09_F_7_1.5_1.5_pbe_n_v1.0.psp8
sparc/psp/10_Ne_8_1.4_1.8_pbe_v1.0.psp8
sparc/psp/11_Na_9_1.8_2.2_pbe_v1.0.psp8
sparc/psp/12_Mg_10_1.9_2.0_pbe_v1.0.psp8
sparc/psp/13_Al_3_1.9_1.9_pbe_n_v1.0.psp8
sparc/psp/14_Si_4_1.9_1.9_pbe_n_v1.0.psp8
sparc/psp/15_P_5_1.8_1.9_pbe_n_v1.0.psp8
sparc/psp/16_S_6_1.8_1.9_pbe_n_v1.0.psp8
sparc/psp/17_Cl_7_1.9_1.9_pbe_n_v1.0.psp8
sparc/psp/18_Ar_8_1.8_1.9_pbe_n_v1.0.psp8
sparc/psp/19_K_9_2.2_2.7_pbe_n_v1.0.psp8
sparc/psp/20_Ca_10_2.3_2.7_pbe_n_v1.0.psp8
sparc/psp/21_Sc_11_2.4_2.5_pbe_n_v1.0.psp8
sparc/psp/22_Ti_12_2.0_2.8_pbe_n_v1.0.psp8
sparc/psp/23_V_13_1.6_1.9_pbe_n_v1.0.psp8
sparc/psp/24_Cr_14_1.7_2.1_pbe_n_v1.0.psp8
sparc/psp/25_Mn_15_1.8_2.3_pbe_n_v1.0.psp8
sparc/psp/26_Fe_16_2.0_2.5_pbe_n_v1.0.psp8
sparc/psp/27_Co_17_1.6_2.2_pbe_n_v1.0.psp8
sparc/psp/28_Ni_18_1.7_2.2_pbe_n_v1.0.psp8
sparc/psp/29_Cu_19_1.7_1.9_pbe_n_v1.0.psp8
sparc/psp/30_Zn_20_1.9_2.3_pbe_n_v1.0.psp8
sparc/psp/31_Ga_13_1.9_2.4_pbe_n_v1.0.psp8
sparc/psp/32_Ge_14_2.2_2.3_pbe_n_v1.0.psp8
sparc/psp/33_As_15_1.8_2.1_pbe_n_v1.0.psp8
sparc/psp/34_Se_16_1.9_2.1_pbe_n_v1.0.psp8
sparc/psp/35_Br_7_2.1_2.2_pbe_n_v1.0.psp8
sparc/psp/36_Kr_8_1.7_2.3_pbe_n_v1.0.psp8
sparc/psp/37_Rb_9_2.8_3.3_pbe_n_v1.0.psp8
sparc/psp/38_Sr_10_2.3_2.5_pbe_n_v1.0.psp8
sparc/psp/39_Y_11_2.1_2.4_pbe_n_v1.0.psp8
sparc/psp/40_Zr_12_2.0_2.5_pbe_n_v1.0.psp8
sparc/psp/41_Nb_13_1.5_1.7_pbe_n_v1.0.psp8
sparc/psp/42_Mo_14_2.0_2.6_pbe_n_v1.0.psp8
sparc_x_api-1.1.0.dist-info/licenses/LICENSE
sparc_x_api-1.1.0.dist-info/METADATA
sparc_x_api-1.1.0.dist-info/WHEEL
sparc_x_api-1.1.0.dist-info/entry_points.txt
sparc_x_api-1.1.0.dist-info/top_level.txt
sparc_x_api-1.1.0.dist-info/RECORD
