Metadata-Version: 2.4
Name: sparc-x-api
Version: 1.1.0
Summary: Python API for the SPARC DFT Code
Home-page: https://github.com/SPARC-X/SPARC-X-API
Author: Tian Tian, Lucas R Timmerman, Ben Comer
Author-email: alchem0x2a@gmail.com, ltimmerman3@gatech.edu, ben.comer@gatech.edu
Requires-Python: >=3.8
License-File: LICENSE
Requires-Dist: ase>=3.22.0
Requires-Dist: numpy>=1.23
Requires-Dist: packaging>=20.0
Requires-Dist: psutil>=5.0.0
Provides-Extra: test
Requires-Dist: pytest; extra == "test"
Requires-Dist: pyfakefs; extra == "test"
Requires-Dist: pytest-cov; extra == "test"
Requires-Dist: black; extra == "test"
Requires-Dist: isort; extra == "test"
Requires-Dist: flake8; extra == "test"
Requires-Dist: anybadge; extra == "test"
Requires-Dist: pre-commit; extra == "test"
Provides-Extra: doc
Requires-Dist: pytest; extra == "doc"
Requires-Dist: pyfakefs; extra == "doc"
Requires-Dist: pytest-cov; extra == "doc"
Requires-Dist: black; extra == "doc"
Requires-Dist: isort; extra == "doc"
Requires-Dist: flake8; extra == "doc"
Requires-Dist: anybadge; extra == "doc"
Requires-Dist: pre-commit; extra == "doc"
Requires-Dist: sphinx_rtd_theme; extra == "doc"
Requires-Dist: sphinx_tabs; extra == "doc"
Requires-Dist: myst-parser; extra == "doc"
Dynamic: author
Dynamic: author-email
Dynamic: description
Dynamic: description-content-type
Dynamic: home-page
Dynamic: license-file
Dynamic: provides-extra
Dynamic: requires-dist
Dynamic: requires-python
Dynamic: summary
